{"theater":"0056","date":"20230518","movieScreenList":[{"title":"분노의 질주-라이드 오어 다이","theater":"cgv","screen":"4관[SCREENX] 8층","time":"09:40","date":"20230518","theater_Id":"0056","movie_Id":null},{"title":"분노의 질주-라이드 오어 다이","theater":"cgv","screen":"4관[SCREENX] 8층","time":"12:30","date":"20230518","theater_Id":"0056","movie_Id":null},{"title":"분노의 질주-라이드 오어 다이","theater":"cgv","screen":"4관[SCREENX] 8층","time":"15:20","date":"20230518","theater_Id":"0056","movie_Id":null},{"title":"분노의 질주-라이드 오어 다이","theater":"cgv","screen":"4관[SCREENX] 8층","time":"18:10","date":"20230518","theater_Id":"0056","movie_Id":null},{"title":"분노의 질주-라이드 오어 다이","theater":"cgv","screen":"4관[SCREENX] 8층","time":"21:00","date":"20230518","theater_Id":"0056","movie_Id":null},{"title":"분노의 질주-라이드 오어 다이","theater":"cgv","screen":"4관[SCREENX] 8층","time":"23:50","date":"20230518","theater_Id":"0056","movie_Id":null},{"title":"분노의 질주-라이드 오어 다이","theater":"cgv","screen":"3관 8층","time":"09:00","date":"20230518","theater_Id":"0056","movie_Id":null},{"title":"분노의 질주-라이드 오어 다이","theater":"cgv","screen":"3관 8층","time":"11:50","date":"20230518","theater_Id":"0056","movie_Id":null},{"title":"분노의 질주-라이드 오어 다이","theater":"cgv","screen":"3관 8층","time":"14:40","date":"20230518","theater_Id":"0056","movie_Id":null},{"title":"분노의 질주-라이드 오어 다이","theater":"cgv","screen":"3관 8층","time":"17:30","date":"20230518","theater_Id":"0056","movie_Id":null},{"title":"분노의 질주-라이드 오어 다이","theater":"cgv","screen":"3관 8층","time":"20:20","date":"20230518","theater_Id":"0056","movie_Id":null},{"title":"분노의 질주-라이드 오어 다이","theater":"cgv","screen":"3관 8층","time":"23:10","date":"20230518","theater_Id":"0056","movie_Id":null}]}