{"theater":"0257","date":"20230515","movieScreenList":[{"title":"슈퍼 마리오 브라더스","theater":"cgv","screen":"4DX","time":"08:40","date":"20230515","theater_Id":"0257","movie_Id":null},{"title":"슈퍼 마리오 브라더스","theater":"cgv","screen":"4DX","time":"10:35","date":"20230515","theater_Id":"0257","movie_Id":null},{"title":"슈퍼 마리오 브라더스","theater":"cgv","screen":"4DX","time":"19:35","date":"20230515","theater_Id":"0257","movie_Id":null},{"title":"슈퍼 마리오 브라더스","theater":"cgv","screen":"4관","time":"14:05","date":"20230515","theater_Id":"0257","movie_Id":null},{"title":"가디언즈 오브 갤럭시-Volume 3","theater":"cgv","screen":"4DX","time":"12:35","date":"20230515","theater_Id":"0257","movie_Id":null},{"title":"가디언즈 오브 갤럭시-Volume 3","theater":"cgv","screen":"4DX","time":"15:35","date":"20230515","theater_Id":"0257","movie_Id":null},{"title":"가디언즈 오브 갤럭시-Volume 3","theater":"cgv","screen":"4DX","time":"21:35","date":"20230515","theater_Id":"0257","movie_Id":null},{"title":"가디언즈 오브 갤럭시-Volume 3","theater":"cgv","screen":"IMAX","time":"08:30","date":"20230515","theater_Id":"0257","movie_Id":null},{"title":"가디언즈 오브 갤럭시-Volume 3","theater":"cgv","screen":"IMAX","time":"11:30","date":"20230515","theater_Id":"0257","movie_Id":null},{"title":"가디언즈 오브 갤럭시-Volume 3","theater":"cgv","screen":"IMAX","time":"14:30","date":"20230515","theater_Id":"0257","movie_Id":null},{"title":"가디언즈 오브 갤럭시-Volume 3","theater":"cgv","screen":"IMAX","time":"17:30","date":"20230515","theater_Id":"0257","movie_Id":null},{"title":"가디언즈 오브 갤럭시-Volume 3","theater":"cgv","screen":"IMAX","time":"20:30","date":"20230515","theater_Id":"0257","movie_Id":null},{"title":"가디언즈 오브 갤럭시-Volume 3","theater":"cgv","screen":"IMAX","time":"23:30","date":"20230515","theater_Id":"0257","movie_Id":null},{"title":"가디언즈 오브 갤럭시-Volume 3","theater":"cgv","screen":"1관","time":"10:40","date":"20230515","theater_Id":"0257","movie_Id":null},{"title":"가디언즈 오브 갤럭시-Volume 3","theater":"cgv","screen":"1관","time":"13:40","date":"20230515","theater_Id":"0257","movie_Id":null},{"title":"가디언즈 오브 갤럭시-Volume 3","theater":"cgv","screen":"1관","time":"16:40","date":"20230515","theater_Id":"0257","movie_Id":null},{"title":"가디언즈 오브 갤럭시-Volume 3","theater":"cgv","screen":"1관","time":"19:40","date":"20230515","theater_Id":"0257","movie_Id":null},{"title":"가디언즈 오브 갤럭시-Volume 3","theater":"cgv","screen":"1관","time":"22:40","date":"20230515","theater_Id":"0257","movie_Id":null},{"title":"가디언즈 오브 갤럭시-Volume 3","theater":"cgv","screen":"3관","time":"18:40","date":"20230515","theater_Id":"0257","movie_Id":null},{"title":"가디언즈 오브 갤럭시-Volume 3","theater":"cgv","screen":"3관","time":"21:45","date":"20230515","theater_Id":"0257","movie_Id":null},{"title":"롱디","theater":"cgv","screen":"1관","time":"08:35","date":"20230515","theater_Id":"0257","movie_Id":null},{"title":"롱디","theater":"cgv","screen":"2관","time":"11:45","date":"20230515","theater_Id":"0257","movie_Id":null},{"title":"롱디","theater":"cgv","screen":"2관","time":"21:15","date":"20230515","theater_Id":"0257","movie_Id":null},{"title":"더 퍼스트 슬램덩크","theater":"cgv","screen":"3관","time":"14:20","date":"20230515","theater_Id":"0257","movie_Id":null},{"title":"문재인입니다","theater":"cgv","screen":"2관","time":"16:25","date":"20230515","theater_Id":"0257","movie_Id":null},{"title":"문재인입니다","theater":"cgv","screen":"3관","time":"12:00","date":"20230515","theater_Id":"0257","movie_Id":null},{"title":"문재인입니다","theater":"cgv","screen":"4관","time":"20:20","date":"20230515","theater_Id":"0257","movie_Id":null},{"title":"극장판 짱구는 못말려-동물소환 닌자 배꼽수비대","theater":"cgv","screen":"4관","time":"09:40","date":"20230515","theater_Id":"0257","movie_Id":null},{"title":"극장판 짱구는 못말려-동물소환 닌자 배꼽수비대","theater":"cgv","screen":"4관","time":"11:50","date":"20230515","theater_Id":"0257","movie_Id":null},{"title":"극장판 짱구는 못말려-동물소환 닌자 배꼽수비대","theater":"cgv","screen":"4관","time":"16:05","date":"20230515","theater_Id":"0257","movie_Id":null},{"title":"극장판 짱구는 못말려-동물소환 닌자 배꼽수비대","theater":"cgv","screen":"4관","time":"18:15","date":"20230515","theater_Id":"0257","movie_Id":null},{"title":"드림","theater":"cgv","screen":"2관","time":"09:10","date":"20230515","theater_Id":"0257","movie_Id":null},{"title":"드림","theater":"cgv","screen":"2관","time":"13:55","date":"20230515","theater_Id":"0257","movie_Id":null},{"title":"드림","theater":"cgv","screen":"2관","time":"23:25","date":"20230515","theater_Id":"0257","movie_Id":null},{"title":"존 윅 4","theater":"cgv","screen":"4관","time":"22:45","date":"20230515","theater_Id":"0257","movie_Id":null},{"title":"스즈메의 문단속","theater":"cgv","screen":"2관","time":"18:45","date":"20230515","theater_Id":"0257","movie_Id":null},{"title":"스즈메의 문단속","theater":"cgv","screen":"3관","time":"09:30","date":"20230515","theater_Id":"0257","movie_Id":null},{"title":"옥수역귀신","theater":"cgv","screen":"3관","time":"16:50","date":"20230515","theater_Id":"0257","movie_Id":null}]}